funcio/__about__.py
funcio/__init__.py
funcio/retries.py
funcio/utils/__init__.py
funcio/utils/exec.py
funcio/utils/parameters.py
funcio-0.0.1a1.dist-info/METADATA
funcio-0.0.1a1.dist-info/WHEEL
funcio-0.0.1a1.dist-info/licenses/LICENSE
funcio-0.0.1a1.dist-info/RECORD
